ciph/__init__.py
ciph/cli.py
ciph-0.1.0.dist-info/licenses/LICENSE
ciph-0.1.0.dist-info/METADATA
ciph-0.1.0.dist-info/WHEEL
ciph-0.1.0.dist-info/entry_points.txt
ciph-0.1.0.dist-info/top_level.txt
ciph-0.1.0.dist-info/RECORD
