Metadata-Version: 2.4
Name: ciph
Version: 0.1.0
Summary: Fast, streaming file encryption for large media files and cloud uploads
Author-email: Ankit Chaubey <m.ankitchaubey@gmail.com>
License: Apache License 2.0
Project-URL: Homepage, https://github.com/ankit-chaubey/ciph
Project-URL: Source, https://github.com/ankit-chaubey/ciph
Project-URL: Issues, https://github.com/ankit-chaubey/ciph/issues
Keywords: encryption,cryptography,security,aes,chacha20,argon2,streaming,files,privacy
Classifier: Development Status :: 4 - Beta
Classifier: Intended Audience :: Developers
Classifier: Topic :: Security :: Cryptography
Classifier: Topic :: System :: Archiving :: Backup
Classifier: License :: OSI Approved :: Apache Software License
Classifier: Programming Language :: C
Classifier: Programming Language :: Python :: 3
Classifier: Programming Language :: Python :: 3 :: Only
Classifier: Operating System :: POSIX :: Linux
Classifier: Operating System :: Unix
Requires-Python: >=3.8
License-File: LICENSE
Requires-Dist: tqdm>=4.60.0
Dynamic: license-file
Dynamic: requires-python
